odoo/addons/storage_backend/README.rst
odoo/addons/storage_backend/__init__.py
odoo/addons/storage_backend/__manifest__.py
odoo/addons/storage_backend/components/__init__.py
odoo/addons/storage_backend/components/base_adapter.py
odoo/addons/storage_backend/components/filesystem_adapter.py
odoo/addons/storage_backend/data/data.xml
odoo/addons/storage_backend/i18n/storage_backend.pot
odoo/addons/storage_backend/models/__init__.py
odoo/addons/storage_backend/models/storage_backend.py
odoo/addons/storage_backend/readme/CONTRIBUTORS.rst
odoo/addons/storage_backend/readme/DESCRIPTION.rst
odoo/addons/storage_backend/readme/HISTORY.rst
odoo/addons/storage_backend/readme/USAGE.rst
odoo/addons/storage_backend/security/ir.model.access.csv
odoo/addons/storage_backend/static/description/icon.png
odoo/addons/storage_backend/static/description/index.html
odoo/addons/storage_backend/tests/__init__.py
odoo/addons/storage_backend/tests/common.py
odoo/addons/storage_backend/tests/test_filesystem.py
odoo/addons/storage_backend/views/backend_storage_view.xml
odoo14_addon_storage_backend-14.0.2.0.6.dist-info/METADATA
odoo14_addon_storage_backend-14.0.2.0.6.dist-info/WHEEL
odoo14_addon_storage_backend-14.0.2.0.6.dist-info/top_level.txt
odoo14_addon_storage_backend-14.0.2.0.6.dist-info/RECORD
